ansible_collections/ansible/posix/CHANGELOG.rst
ansible_collections/ansible/posix/COPYING
ansible_collections/ansible/posix/PSF-license.txt
ansible_collections/ansible/posix/README.md
ansible_collections/ansible/posix/bindep.txt
ansible_collections/ansible/posix/codecov.yml
ansible_collections/ansible/posix/galaxy.yml
ansible_collections/ansible/posix/requirements.txt
ansible_collections/ansible/posix/shippable.yml
ansible_collections/ansible/posix/test-requirements.txt
ansible_collections/ansible/posix/changelogs/changelog.yaml
ansible_collections/ansible/posix/changelogs/config.yaml
ansible_collections/ansible/posix/changelogs/fragments/.keep
ansible_collections/ansible/posix/hacking/cgroup_perf_recap_graph.py
ansible_collections/ansible/posix/meta/runtime.yml
ansible_collections/ansible/posix/plugins/action/__init__.py
ansible_collections/ansible/posix/plugins/action/patch.py
ansible_collections/ansible/posix/plugins/action/synchronize.py
ansible_collections/ansible/posix/plugins/callback/__init__.py
ansible_collections/ansible/posix/plugins/callback/cgroup_perf_recap.py
ansible_collections/ansible/posix/plugins/callback/debug.py
ansible_collections/ansible/posix/plugins/callback/json.py
ansible_collections/ansible/posix/plugins/callback/jsonl.py
ansible_collections/ansible/posix/plugins/callback/profile_roles.py
ansible_collections/ansible/posix/plugins/callback/profile_tasks.py
ansible_collections/ansible/posix/plugins/callback/skippy.py
ansible_collections/ansible/posix/plugins/callback/timer.py
ansible_collections/ansible/posix/plugins/module_utils/__init__.py
ansible_collections/ansible/posix/plugins/module_utils/_version.py
ansible_collections/ansible/posix/plugins/module_utils/firewalld.py
ansible_collections/ansible/posix/plugins/module_utils/mount.py
ansible_collections/ansible/posix/plugins/module_utils/version.py
ansible_collections/ansible/posix/plugins/modules/__init__.py
ansible_collections/ansible/posix/plugins/modules/acl.py
enoslib_ansible-10.1.0.0.dist-info/LICENCE
enoslib_ansible-10.1.0.0.dist-info/METADATA
enoslib_ansible-10.1.0.0.dist-info/WHEEL
enoslib_ansible-10.1.0.0.dist-info/top_level.txt
enoslib_ansible-10.1.0.0.dist-info/RECORD
