Metadata-Version: 2.1
Name: enoslib-ansible
Version: 10.1.0.0
Summary: Radically simple IT automation -- For EnOSlib !
Home-page: https://discovery.gitlabpages.inria.fr/enoslib/
Author: EnOSlib team
Author-email: enoslib.contact@inria.fr
License: GPLv3+
Classifier: Development Status :: 5 - Production/Stable
Classifier: Environment :: Console
Classifier: Framework :: Ansible
Classifier: Intended Audience :: Developers
Classifier: Intended Audience :: Information Technology
Classifier: Intended Audience :: System Administrators
Classifier: License :: OSI Approved :: GNU General Public License v3 or later (GPLv3+)
Classifier: Natural Language :: English
Classifier: Operating System :: POSIX
Classifier: Topic :: System :: Installation/Setup
Classifier: Topic :: System :: Systems Administration
Classifier: Topic :: Utilities
License-File: LICENCE
Requires-Dist: ansible-core ~=2.17.0
